checklang/__init__.py
checklang/init.py
checklang/lid.176.ftz
checklang-0.1.0.dist-info/METADATA
checklang-0.1.0.dist-info/WHEEL
checklang-0.1.0.dist-info/top_level.txt
checklang-0.1.0.dist-info/RECORD
