Metadata-Version: 2.4
Name: checklang
Version: 0.1.0
Summary: a language utils module
Author-email: Yu Moqing <yumoqing@gmail.com>
License: MIT
Requires-Dist: fasttext
Requires-Dist: ahserver
Requires-Dist: sqlor
Requires-Dist: appPublic
